mailmojo_sdk/__init__.py
mailmojo_sdk/api_client.py
mailmojo_sdk/configuration.py
mailmojo_sdk/rest.py
mailmojo_sdk/api/__init__.py
mailmojo_sdk/api/account_api.py
mailmojo_sdk/api/automation_api.py
mailmojo_sdk/api/contact_api.py
mailmojo_sdk/api/embed_api.py
mailmojo_sdk/api/form_api.py
mailmojo_sdk/api/list_api.py
mailmojo_sdk/api/newsletter_api.py
mailmojo_sdk/api/page_api.py
mailmojo_sdk/api/segment_api.py
mailmojo_sdk/api/template_api.py
mailmojo_sdk/api/webhook_api.py
mailmojo_sdk/models/__init__.py
mailmojo_sdk/models/add_form_subscriber.py
mailmojo_sdk/models/base_contact.py
mailmojo_sdk/models/campaign_detail.py
mailmojo_sdk/models/campaign_statistics.py
mailmojo_sdk/models/category.py
mailmojo_sdk/models/contact.py
mailmojo_sdk/models/contact_list.py
mailmojo_sdk/models/contacts.py
mailmojo_sdk/models/domain.py
mailmojo_sdk/models/embed.py
mailmojo_sdk/models/embed_options.py
mailmojo_sdk/models/form.py
mailmojo_sdk/models/form_conversion.py
mailmojo_sdk/models/historical_contacts_stats.py
mailmojo_sdk/models/import_result.py
mailmojo_sdk/models/inline_response200.py
mailmojo_sdk/models/list.py
mailmojo_sdk/models/list_detail.py
mailmojo_sdk/models/minimal_segment.py
mailmojo_sdk/models/newsletter_creation.py
mailmojo_sdk/models/newsletter_detail.py
mailmojo_sdk/models/newsletter_send.py
mailmojo_sdk/models/newsletter_send_test.py
mailmojo_sdk/models/newsletter_update.py
mailmojo_sdk/models/page.py
mailmojo_sdk/models/page_meta.py
mailmojo_sdk/models/schema.py
mailmojo_sdk/models/segment.py
mailmojo_sdk/models/segment_creation.py
mailmojo_sdk/models/segment_tag_predicate.py
mailmojo_sdk/models/statistics.py
mailmojo_sdk/models/subscriber.py
mailmojo_sdk/models/template.py
mailmojo_sdk/models/track_form_view.py
mailmojo_sdk/models/track_page_view.py
mailmojo_sdk/models/user.py
mailmojo_sdk/models/user_creation.py
mailmojo_sdk/models/webhook_creation.py
test/__init__.py
test/test_account_api.py
test/test_add_form_subscriber.py
test/test_automation_api.py
mailmojo_sdk-0.6.0.dist-info/LICENSE
mailmojo_sdk-0.6.0.dist-info/METADATA
mailmojo_sdk-0.6.0.dist-info/WHEEL
mailmojo_sdk-0.6.0.dist-info/top_level.txt
mailmojo_sdk-0.6.0.dist-info/RECORD
