Metadata-Version: 2.1
Name: mailmojo-sdk
Version: 0.6.0
Summary: MailMojo API
Home-page: https://github.com/eliksir/mailmojo-python-sdk
Author: Eliksir AS
Author-email: hjelp@mailmojo.no
License: Apache
Keywords: Swagger,MailMojo
Platform: UNKNOWN
Classifier: Development Status :: 4 - Beta
Classifier: Intended Audience :: Developers
Classifier: Topic :: Software Development :: Libraries :: Python Modules
Classifier: License :: OSI Approved :: Apache Software License
Classifier: Programming Language :: Python :: 2
Classifier: Programming Language :: Python :: 2.7
Classifier: Programming Language :: Python :: 3
Classifier: Programming Language :: Python :: 3.4
Requires-Dist: urllib3 (>=1.15)
Requires-Dist: six (>=1.10)
Requires-Dist: certifi
Requires-Dist: python-dateutil
